pyandrozoo/__init__.py
pyandrozoo/api.py
pyandrozoo-0.3.2.dist-info/METADATA
pyandrozoo-0.3.2.dist-info/WHEEL
pyandrozoo-0.3.2.dist-info/RECORD
