Metadata-Version: 2.3
Name: pyAndroZoo
Version: 0.3.2
Summary: A Python library to access the AndroZoo data set.
License: GPL-3.0-or-later
Keywords: android,androzoo,malware,apk
Author: Cédric Bonhomme
Author-email: cedric@cedricbonhomme.org
Requires-Python: >=3.10,<4.0
Classifier: Development Status :: 5 - Production/Stable
Classifier: Environment :: Console
Classifier: Intended Audience :: Developers
Classifier: Intended Audience :: Science/Research
Classifier: License :: OSI Approved :: GNU General Public License v3 or later (GPLv3+)
Classifier: Operating System :: POSIX :: Linux
Classifier: Programming Language :: Python :: 3
Classifier: Programming Language :: Python :: 3.10
Classifier: Programming Language :: Python :: 3.11
Classifier: Programming Language :: Python :: 3.12
Classifier: Programming Language :: Python :: 3.13
Classifier: Topic :: Security
Requires-Dist: grequests (>=0.7.0)
Project-URL: Changelog, https://github.com/ICC-analysis/pyAndroZoo/blob/master/CHANGELOG.rst
Project-URL: Homepage, https://github.com/ICC-analysis/pyAndroZoo
Project-URL: Repository, https://github.com/ICC-analysis/pyAndroZoo
